{
  "family": "tdcc",
  "publication_date": "2026-04-17",
  "ticker": "3231",
  "status": "accepted",
  "filtered_rows": 16,
  "http_status": 200,
  "response_bytes": 77466,
  "source_url": "https://www.tdcc.com.tw/portal/zh/smWeb/qryStock",
  "source_hash": "cb8be4db7db034305d4ad9e60e7ef96926aa2aa1542edc7781b76f515ffd6551",
  "retrieval_time_utc": "2026-07-21T11:11:15+00:00",
  "error": "",
  "rows": [
    {
      "publication_date": "2026-04-17",
      "ticker": "3231",
      "market": "TWSE",
      "holding_bucket": "1-999",
      "holder_count": 119280,
      "shares": 26417676,
      "share_pct": 0.83,
      "source_quality": "official_tdcc_retained_history",
      "market_available_at": "2026-04-17",
      "available_at_policy": "official publication date only; exact time blocked; no prior-week backfill",
      "source_url": "https://www.tdcc.com.tw/portal/zh/smWeb/qryStock",
      "source_hash": "cb8be4db7db034305d4ad9e60e7ef96926aa2aa1542edc7781b76f515ffd6551",
      "retrieval_time_utc": "2026-07-21T11:11:15+00:00"
    },
    {
      "publication_date": "2026-04-17",
      "ticker": "3231",
      "market": "TWSE",
      "holding_bucket": "1,000-5,000",
      "holder_count": 231582,
      "shares": 457129844,
      "share_pct": 14.37,
      "source_quality": "official_tdcc_retained_history",
      "market_available_at": "2026-04-17",
      "available_at_policy": "official publication date only; exact time blocked; no prior-week backfill",
      "source_url": "https://www.tdcc.com.tw/portal/zh/smWeb/qryStock",
      "source_hash": "cb8be4db7db034305d4ad9e60e7ef96926aa2aa1542edc7781b76f515ffd6551",
      "retrieval_time_utc": "2026-07-21T11:11:15+00:00"
    },
    {
      "publication_date": "2026-04-17",
      "ticker": "3231",
      "market": "TWSE",
      "holding_bucket": "5,001-10,000",
      "holder_count": 27023,
      "shares": 208569245,
      "share_pct": 6.55,
      "source_quality": "official_tdcc_retained_history",
      "market_available_at": "2026-04-17",
      "available_at_policy": "official publication date only; exact time blocked; no prior-week backfill",
      "source_url": "https://www.tdcc.com.tw/portal/zh/smWeb/qryStock",
      "source_hash": "cb8be4db7db034305d4ad9e60e7ef96926aa2aa1542edc7781b76f515ffd6551",
      "retrieval_time_utc": "2026-07-21T11:11:15+00:00"
    },
    {
      "publication_date": "2026-04-17",
      "ticker": "3231",
      "market": "TWSE",
      "holding_bucket": "10,001-15,000",
      "holder_count": 7747,
      "shares": 98349716,
      "share_pct": 3.09,
      "source_quality": "official_tdcc_retained_history",
      "market_available_at": "2026-04-17",
      "available_at_policy": "official publication date only; exact time blocked; no prior-week backfill",
      "source_url": "https://www.tdcc.com.tw/portal/zh/smWeb/qryStock",
      "source_hash": "cb8be4db7db034305d4ad9e60e7ef96926aa2aa1542edc7781b76f515ffd6551",
      "retrieval_time_utc": "2026-07-21T11:11:15+00:00"
    },
    {
      "publication_date": "2026-04-17",
      "ticker": "3231",
      "market": "TWSE",
      "holding_bucket": "15,001-20,000",
      "holder_count": 4342,
      "shares": 80102919,
      "share_pct": 2.51,
      "source_quality": "official_tdcc_retained_history",
      "market_available_at": "2026-04-17",
      "available_at_policy": "official publication date only; exact time blocked; no prior-week backfill",
      "source_url": "https://www.tdcc.com.tw/portal/zh/smWeb/qryStock",
      "source_hash": "cb8be4db7db034305d4ad9e60e7ef96926aa2aa1542edc7781b76f515ffd6551",
      "retrieval_time_utc": "2026-07-21T11:11:15+00:00"
    },
    {
      "publication_date": "2026-04-17",
      "ticker": "3231",
      "market": "TWSE",
      "holding_bucket": "20,001-30,000",
      "holder_count": 3371,
      "shares": 85874731,
      "share_pct": 2.7,
      "source_quality": "official_tdcc_retained_history",
      "market_available_at": "2026-04-17",
      "available_at_policy": "official publication date only; exact time blocked; no prior-week backfill",
      "source_url": "https://www.tdcc.com.tw/portal/zh/smWeb/qryStock",
      "source_hash": "cb8be4db7db034305d4ad9e60e7ef96926aa2aa1542edc7781b76f515ffd6551",
      "retrieval_time_utc": "2026-07-21T11:11:15+00:00"
    },
    {
      "publication_date": "2026-04-17",
      "ticker": "3231",
      "market": "TWSE",
      "holding_bucket": "30,001-40,000",
      "holder_count": 1389,
      "shares": 49494861,
      "share_pct": 1.55,
      "source_quality": "official_tdcc_retained_history",
      "market_available_at": "2026-04-17",
      "available_at_policy": "official publication date only; exact time blocked; no prior-week backfill",
      "source_url": "https://www.tdcc.com.tw/portal/zh/smWeb/qryStock",
      "source_hash": "cb8be4db7db034305d4ad9e60e7ef96926aa2aa1542edc7781b76f515ffd6551",
      "retrieval_time_utc": "2026-07-21T11:11:15+00:00"
    },
    {
      "publication_date": "2026-04-17",
      "ticker": "3231",
      "market": "TWSE",
      "holding_bucket": "40,001-50,000",
      "holder_count": 890,
      "shares": 41224550,
      "share_pct": 1.29,
      "source_quality": "official_tdcc_retained_history",
      "market_available_at": "2026-04-17",
      "available_at_policy": "official publication date only; exact time blocked; no prior-week backfill",
      "source_url": "https://www.tdcc.com.tw/portal/zh/smWeb/qryStock",
      "source_hash": "cb8be4db7db034305d4ad9e60e7ef96926aa2aa1542edc7781b76f515ffd6551",
      "retrieval_time_utc": "2026-07-21T11:11:15+00:00"
    },
    {
      "publication_date": "2026-04-17",
      "ticker": "3231",
      "market": "TWSE",
      "holding_bucket": "50,001-100,000",
      "holder_count": 1485,
      "shares": 106277160,
      "share_pct": 3.34,
      "source_quality": "official_tdcc_retained_history",
      "market_available_at": "2026-04-17",
      "available_at_policy": "official publication date only; exact time blocked; no prior-week backfill",
      "source_url": "https://www.tdcc.com.tw/portal/zh/smWeb/qryStock",
      "source_hash": "cb8be4db7db034305d4ad9e60e7ef96926aa2aa1542edc7781b76f515ffd6551",
      "retrieval_time_utc": "2026-07-21T11:11:15+00:00"
    },
    {
      "publication_date": "2026-04-17",
      "ticker": "3231",
      "market": "TWSE",
      "holding_bucket": "100,001-200,000",
      "holder_count": 655,
      "shares": 92772296,
      "share_pct": 2.91,
      "source_quality": "official_tdcc_retained_history",
      "market_available_at": "2026-04-17",
      "available_at_policy": "official publication date only; exact time blocked; no prior-week backfill",
      "source_url": "https://www.tdcc.com.tw/portal/zh/smWeb/qryStock",
      "source_hash": "cb8be4db7db034305d4ad9e60e7ef96926aa2aa1542edc7781b76f515ffd6551",
      "retrieval_time_utc": "2026-07-21T11:11:15+00:00"
    },
    {
      "publication_date": "2026-04-17",
      "ticker": "3231",
      "market": "TWSE",
      "holding_bucket": "200,001-400,000",
      "holder_count": 280,
      "shares": 79383041,
      "share_pct": 2.49,
      "source_quality": "official_tdcc_retained_history",
      "market_available_at": "2026-04-17",
      "available_at_policy": "official publication date only; exact time blocked; no prior-week backfill",
      "source_url": "https://www.tdcc.com.tw/portal/zh/smWeb/qryStock",
      "source_hash": "cb8be4db7db034305d4ad9e60e7ef96926aa2aa1542edc7781b76f515ffd6551",
      "retrieval_time_utc": "2026-07-21T11:11:15+00:00"
    },
    {
      "publication_date": "2026-04-17",
      "ticker": "3231",
      "market": "TWSE",
      "holding_bucket": "400,001-600,000",
      "holder_count": 129,
      "shares": 62994045,
      "share_pct": 1.98,
      "source_quality": "official_tdcc_retained_history",
      "market_available_at": "2026-04-17",
      "available_at_policy": "official publication date only; exact time blocked; no prior-week backfill",
      "source_url": "https://www.tdcc.com.tw/portal/zh/smWeb/qryStock",
      "source_hash": "cb8be4db7db034305d4ad9e60e7ef96926aa2aa1542edc7781b76f515ffd6551",
      "retrieval_time_utc": "2026-07-21T11:11:15+00:00"
    },
    {
      "publication_date": "2026-04-17",
      "ticker": "3231",
      "market": "TWSE",
      "holding_bucket": "600,001-800,000",
      "holder_count": 69,
      "shares": 48090828,
      "share_pct": 1.51,
      "source_quality": "official_tdcc_retained_history",
      "market_available_at": "2026-04-17",
      "available_at_policy": "official publication date only; exact time blocked; no prior-week backfill",
      "source_url": "https://www.tdcc.com.tw/portal/zh/smWeb/qryStock",
      "source_hash": "cb8be4db7db034305d4ad9e60e7ef96926aa2aa1542edc7781b76f515ffd6551",
      "retrieval_time_utc": "2026-07-21T11:11:15+00:00"
    },
    {
      "publication_date": "2026-04-17",
      "ticker": "3231",
      "market": "TWSE",
      "holding_bucket": "800,001-1,000,000",
      "holder_count": 26,
      "shares": 23768500,
      "share_pct": 0.74,
      "source_quality": "official_tdcc_retained_history",
      "market_available_at": "2026-04-17",
      "available_at_policy": "official publication date only; exact time blocked; no prior-week backfill",
      "source_url": "https://www.tdcc.com.tw/portal/zh/smWeb/qryStock",
      "source_hash": "cb8be4db7db034305d4ad9e60e7ef96926aa2aa1542edc7781b76f515ffd6551",
      "retrieval_time_utc": "2026-07-21T11:11:15+00:00"
    },
    {
      "publication_date": "2026-04-17",
      "ticker": "3231",
      "market": "TWSE",
      "holding_bucket": "1,000,001以上",
      "holder_count": 275,
      "shares": 1719967838,
      "share_pct": 54.08,
      "source_quality": "official_tdcc_retained_history",
      "market_available_at": "2026-04-17",
      "available_at_policy": "official publication date only; exact time blocked; no prior-week backfill",
      "source_url": "https://www.tdcc.com.tw/portal/zh/smWeb/qryStock",
      "source_hash": "cb8be4db7db034305d4ad9e60e7ef96926aa2aa1542edc7781b76f515ffd6551",
      "retrieval_time_utc": "2026-07-21T11:11:15+00:00"
    },
    {
      "publication_date": "2026-04-17",
      "ticker": "3231",
      "market": "TWSE",
      "holding_bucket": "合　計",
      "holder_count": 398543,
      "shares": 3180412250,
      "share_pct": 100.0,
      "source_quality": "official_tdcc_retained_history",
      "market_available_at": "2026-04-17",
      "available_at_policy": "official publication date only; exact time blocked; no prior-week backfill",
      "source_url": "https://www.tdcc.com.tw/portal/zh/smWeb/qryStock",
      "source_hash": "cb8be4db7db034305d4ad9e60e7ef96926aa2aa1542edc7781b76f515ffd6551",
      "retrieval_time_utc": "2026-07-21T11:11:15+00:00"
    }
  ]
}
