{
  "family": "margin",
  "date": "2026-07-16",
  "status": "accepted",
  "filtered_rows": 7,
  "http_status": 200,
  "response_bytes": 127452,
  "source_url": "https://www.twse.com.tw/exchangeReport/MI_MARGN?date=20260716&selectType=ALL&response=json",
  "source_hash": "39049e5c9bc79595ce43054e3928f2d59c7a20e5b85c7b4fe58383167cf3d48e",
  "retrieval_time_utc": "2026-07-21T11:09:51+00:00",
  "error": "",
  "rows": [
    {
      "date": "2026-07-16",
      "ticker": "2308",
      "name": "台達電",
      "market": "TWSE",
      "margin_balance": 7831,
      "short_balance": 3,
      "source_quality": "official_twse_MI_MARGN",
      "source_url": "https://www.twse.com.tw/exchangeReport/MI_MARGN?date=20260716&selectType=ALL&response=json",
      "source_hash": "39049e5c9bc79595ce43054e3928f2d59c7a20e5b85c7b4fe58383167cf3d48e",
      "retrieval_time_utc": "2026-07-21T11:09:51+00:00",
      "available_at_policy": "post_close_release; eligible_next_trading_day_only",
      "source_reuse": "new_official_market_day"
    },
    {
      "date": "2026-07-16",
      "ticker": "2317",
      "name": "鴻海",
      "market": "TWSE",
      "margin_balance": 57196,
      "short_balance": 6,
      "source_quality": "official_twse_MI_MARGN",
      "source_url": "https://www.twse.com.tw/exchangeReport/MI_MARGN?date=20260716&selectType=ALL&response=json",
      "source_hash": "39049e5c9bc79595ce43054e3928f2d59c7a20e5b85c7b4fe58383167cf3d48e",
      "retrieval_time_utc": "2026-07-21T11:09:51+00:00",
      "available_at_policy": "post_close_release; eligible_next_trading_day_only",
      "source_reuse": "new_official_market_day"
    },
    {
      "date": "2026-07-16",
      "ticker": "2330",
      "name": "台積電",
      "market": "TWSE",
      "margin_balance": 32918,
      "short_balance": 5,
      "source_quality": "official_twse_MI_MARGN",
      "source_url": "https://www.twse.com.tw/exchangeReport/MI_MARGN?date=20260716&selectType=ALL&response=json",
      "source_hash": "39049e5c9bc79595ce43054e3928f2d59c7a20e5b85c7b4fe58383167cf3d48e",
      "retrieval_time_utc": "2026-07-21T11:09:51+00:00",
      "available_at_policy": "post_close_release; eligible_next_trading_day_only",
      "source_reuse": "new_official_market_day"
    },
    {
      "date": "2026-07-16",
      "ticker": "2382",
      "name": "廣達",
      "market": "TWSE",
      "margin_balance": 12480,
      "short_balance": 214,
      "source_quality": "official_twse_MI_MARGN",
      "source_url": "https://www.twse.com.tw/exchangeReport/MI_MARGN?date=20260716&selectType=ALL&response=json",
      "source_hash": "39049e5c9bc79595ce43054e3928f2d59c7a20e5b85c7b4fe58383167cf3d48e",
      "retrieval_time_utc": "2026-07-21T11:09:51+00:00",
      "available_at_policy": "post_close_release; eligible_next_trading_day_only",
      "source_reuse": "new_official_market_day"
    },
    {
      "date": "2026-07-16",
      "ticker": "2454",
      "name": "聯發科",
      "market": "TWSE",
      "margin_balance": 9868,
      "short_balance": 4,
      "source_quality": "official_twse_MI_MARGN",
      "source_url": "https://www.twse.com.tw/exchangeReport/MI_MARGN?date=20260716&selectType=ALL&response=json",
      "source_hash": "39049e5c9bc79595ce43054e3928f2d59c7a20e5b85c7b4fe58383167cf3d48e",
      "retrieval_time_utc": "2026-07-21T11:09:51+00:00",
      "available_at_policy": "post_close_release; eligible_next_trading_day_only",
      "source_reuse": "new_official_market_day"
    },
    {
      "date": "2026-07-16",
      "ticker": "3231",
      "name": "緯創",
      "market": "TWSE",
      "margin_balance": 48582,
      "short_balance": 4,
      "source_quality": "official_twse_MI_MARGN",
      "source_url": "https://www.twse.com.tw/exchangeReport/MI_MARGN?date=20260716&selectType=ALL&response=json",
      "source_hash": "39049e5c9bc79595ce43054e3928f2d59c7a20e5b85c7b4fe58383167cf3d48e",
      "retrieval_time_utc": "2026-07-21T11:09:51+00:00",
      "available_at_policy": "post_close_release; eligible_next_trading_day_only",
      "source_reuse": "new_official_market_day"
    },
    {
      "date": "2026-07-16",
      "ticker": "6669",
      "name": "緯穎",
      "market": "TWSE",
      "margin_balance": 1903,
      "short_balance": 0,
      "source_quality": "official_twse_MI_MARGN",
      "source_url": "https://www.twse.com.tw/exchangeReport/MI_MARGN?date=20260716&selectType=ALL&response=json",
      "source_hash": "39049e5c9bc79595ce43054e3928f2d59c7a20e5b85c7b4fe58383167cf3d48e",
      "retrieval_time_utc": "2026-07-21T11:09:51+00:00",
      "available_at_policy": "post_close_release; eligible_next_trading_day_only",
      "source_reuse": "new_official_market_day"
    }
  ]
}
