{
  "family": "tdcc",
  "publication_date": "2025-10-23",
  "ticker": "2308",
  "status": "accepted",
  "filtered_rows": 15,
  "http_status": 200,
  "response_bytes": 76798,
  "source_url": "https://www.tdcc.com.tw/portal/zh/smWeb/qryStock",
  "source_hash": "c4a30e9b028da734ddb57229cb48883905f0d8a6da1354267510528938278602",
  "retrieval_time_utc": "2026-07-21T11:10:45+00:00",
  "error": "",
  "rows": [
    {
      "publication_date": "2025-10-23",
      "ticker": "2308",
      "market": "TWSE",
      "holding_bucket": "1-999",
      "holder_count": 146642,
      "shares": 18623437,
      "share_pct": 0.71,
      "source_quality": "official_tdcc_retained_history",
      "market_available_at": "2025-10-23",
      "available_at_policy": "official publication date only; exact time blocked; no prior-week backfill",
      "source_url": "https://www.tdcc.com.tw/portal/zh/smWeb/qryStock",
      "source_hash": "c4a30e9b028da734ddb57229cb48883905f0d8a6da1354267510528938278602",
      "retrieval_time_utc": "2026-07-21T11:10:45+00:00"
    },
    {
      "publication_date": "2025-10-23",
      "ticker": "2308",
      "market": "TWSE",
      "holding_bucket": "1,000-5,000",
      "holder_count": 50278,
      "shares": 83714410,
      "share_pct": 3.22,
      "source_quality": "official_tdcc_retained_history",
      "market_available_at": "2025-10-23",
      "available_at_policy": "official publication date only; exact time blocked; no prior-week backfill",
      "source_url": "https://www.tdcc.com.tw/portal/zh/smWeb/qryStock",
      "source_hash": "c4a30e9b028da734ddb57229cb48883905f0d8a6da1354267510528938278602",
      "retrieval_time_utc": "2026-07-21T11:10:45+00:00"
    },
    {
      "publication_date": "2025-10-23",
      "ticker": "2308",
      "market": "TWSE",
      "holding_bucket": "5,001-10,000",
      "holder_count": 3398,
      "shares": 25093413,
      "share_pct": 0.96,
      "source_quality": "official_tdcc_retained_history",
      "market_available_at": "2025-10-23",
      "available_at_policy": "official publication date only; exact time blocked; no prior-week backfill",
      "source_url": "https://www.tdcc.com.tw/portal/zh/smWeb/qryStock",
      "source_hash": "c4a30e9b028da734ddb57229cb48883905f0d8a6da1354267510528938278602",
      "retrieval_time_utc": "2026-07-21T11:10:45+00:00"
    },
    {
      "publication_date": "2025-10-23",
      "ticker": "2308",
      "market": "TWSE",
      "holding_bucket": "10,001-15,000",
      "holder_count": 1043,
      "shares": 13049247,
      "share_pct": 0.5,
      "source_quality": "official_tdcc_retained_history",
      "market_available_at": "2025-10-23",
      "available_at_policy": "official publication date only; exact time blocked; no prior-week backfill",
      "source_url": "https://www.tdcc.com.tw/portal/zh/smWeb/qryStock",
      "source_hash": "c4a30e9b028da734ddb57229cb48883905f0d8a6da1354267510528938278602",
      "retrieval_time_utc": "2026-07-21T11:10:45+00:00"
    },
    {
      "publication_date": "2025-10-23",
      "ticker": "2308",
      "market": "TWSE",
      "holding_bucket": "15,001-20,000",
      "holder_count": 495,
      "shares": 8825488,
      "share_pct": 0.33,
      "source_quality": "official_tdcc_retained_history",
      "market_available_at": "2025-10-23",
      "available_at_policy": "official publication date only; exact time blocked; no prior-week backfill",
      "source_url": "https://www.tdcc.com.tw/portal/zh/smWeb/qryStock",
      "source_hash": "c4a30e9b028da734ddb57229cb48883905f0d8a6da1354267510528938278602",
      "retrieval_time_utc": "2026-07-21T11:10:45+00:00"
    },
    {
      "publication_date": "2025-10-23",
      "ticker": "2308",
      "market": "TWSE",
      "holding_bucket": "20,001-30,000",
      "holder_count": 528,
      "shares": 13129641,
      "share_pct": 0.5,
      "source_quality": "official_tdcc_retained_history",
      "market_available_at": "2025-10-23",
      "available_at_policy": "official publication date only; exact time blocked; no prior-week backfill",
      "source_url": "https://www.tdcc.com.tw/portal/zh/smWeb/qryStock",
      "source_hash": "c4a30e9b028da734ddb57229cb48883905f0d8a6da1354267510528938278602",
      "retrieval_time_utc": "2026-07-21T11:10:45+00:00"
    },
    {
      "publication_date": "2025-10-23",
      "ticker": "2308",
      "market": "TWSE",
      "holding_bucket": "30,001-40,000",
      "holder_count": 300,
      "shares": 10472399,
      "share_pct": 0.4,
      "source_quality": "official_tdcc_retained_history",
      "market_available_at": "2025-10-23",
      "available_at_policy": "official publication date only; exact time blocked; no prior-week backfill",
      "source_url": "https://www.tdcc.com.tw/portal/zh/smWeb/qryStock",
      "source_hash": "c4a30e9b028da734ddb57229cb48883905f0d8a6da1354267510528938278602",
      "retrieval_time_utc": "2026-07-21T11:10:45+00:00"
    },
    {
      "publication_date": "2025-10-23",
      "ticker": "2308",
      "market": "TWSE",
      "holding_bucket": "40,001-50,000",
      "holder_count": 199,
      "shares": 9074839,
      "share_pct": 0.34,
      "source_quality": "official_tdcc_retained_history",
      "market_available_at": "2025-10-23",
      "available_at_policy": "official publication date only; exact time blocked; no prior-week backfill",
      "source_url": "https://www.tdcc.com.tw/portal/zh/smWeb/qryStock",
      "source_hash": "c4a30e9b028da734ddb57229cb48883905f0d8a6da1354267510528938278602",
      "retrieval_time_utc": "2026-07-21T11:10:45+00:00"
    },
    {
      "publication_date": "2025-10-23",
      "ticker": "2308",
      "market": "TWSE",
      "holding_bucket": "50,001-100,000",
      "holder_count": 585,
      "shares": 42243753,
      "share_pct": 1.62,
      "source_quality": "official_tdcc_retained_history",
      "market_available_at": "2025-10-23",
      "available_at_policy": "official publication date only; exact time blocked; no prior-week backfill",
      "source_url": "https://www.tdcc.com.tw/portal/zh/smWeb/qryStock",
      "source_hash": "c4a30e9b028da734ddb57229cb48883905f0d8a6da1354267510528938278602",
      "retrieval_time_utc": "2026-07-21T11:10:45+00:00"
    },
    {
      "publication_date": "2025-10-23",
      "ticker": "2308",
      "market": "TWSE",
      "holding_bucket": "100,001-200,000",
      "holder_count": 460,
      "shares": 65756321,
      "share_pct": 2.53,
      "source_quality": "official_tdcc_retained_history",
      "market_available_at": "2025-10-23",
      "available_at_policy": "official publication date only; exact time blocked; no prior-week backfill",
      "source_url": "https://www.tdcc.com.tw/portal/zh/smWeb/qryStock",
      "source_hash": "c4a30e9b028da734ddb57229cb48883905f0d8a6da1354267510528938278602",
      "retrieval_time_utc": "2026-07-21T11:10:45+00:00"
    },
    {
      "publication_date": "2025-10-23",
      "ticker": "2308",
      "market": "TWSE",
      "holding_bucket": "200,001-400,000",
      "holder_count": 319,
      "shares": 90390824,
      "share_pct": 3.47,
      "source_quality": "official_tdcc_retained_history",
      "market_available_at": "2025-10-23",
      "available_at_policy": "official publication date only; exact time blocked; no prior-week backfill",
      "source_url": "https://www.tdcc.com.tw/portal/zh/smWeb/qryStock",
      "source_hash": "c4a30e9b028da734ddb57229cb48883905f0d8a6da1354267510528938278602",
      "retrieval_time_utc": "2026-07-21T11:10:45+00:00"
    },
    {
      "publication_date": "2025-10-23",
      "ticker": "2308",
      "market": "TWSE",
      "holding_bucket": "400,001-600,000",
      "holder_count": 170,
      "shares": 83732684,
      "share_pct": 3.22,
      "source_quality": "official_tdcc_retained_history",
      "market_available_at": "2025-10-23",
      "available_at_policy": "official publication date only; exact time blocked; no prior-week backfill",
      "source_url": "https://www.tdcc.com.tw/portal/zh/smWeb/qryStock",
      "source_hash": "c4a30e9b028da734ddb57229cb48883905f0d8a6da1354267510528938278602",
      "retrieval_time_utc": "2026-07-21T11:10:45+00:00"
    },
    {
      "publication_date": "2025-10-23",
      "ticker": "2308",
      "market": "TWSE",
      "holding_bucket": "600,001-800,000",
      "holder_count": 86,
      "shares": 60401232,
      "share_pct": 2.32,
      "source_quality": "official_tdcc_retained_history",
      "market_available_at": "2025-10-23",
      "available_at_policy": "official publication date only; exact time blocked; no prior-week backfill",
      "source_url": "https://www.tdcc.com.tw/portal/zh/smWeb/qryStock",
      "source_hash": "c4a30e9b028da734ddb57229cb48883905f0d8a6da1354267510528938278602",
      "retrieval_time_utc": "2026-07-21T11:10:45+00:00"
    },
    {
      "publication_date": "2025-10-23",
      "ticker": "2308",
      "market": "TWSE",
      "holding_bucket": "800,001-1,000,000",
      "holder_count": 63,
      "shares": 56409694,
      "share_pct": 2.17,
      "source_quality": "official_tdcc_retained_history",
      "market_available_at": "2025-10-23",
      "available_at_policy": "official publication date only; exact time blocked; no prior-week backfill",
      "source_url": "https://www.tdcc.com.tw/portal/zh/smWeb/qryStock",
      "source_hash": "c4a30e9b028da734ddb57229cb48883905f0d8a6da1354267510528938278602",
      "retrieval_time_utc": "2026-07-21T11:10:45+00:00"
    },
    {
      "publication_date": "2025-10-23",
      "ticker": "2308",
      "market": "TWSE",
      "holding_bucket": "1,000,001以上",
      "holder_count": 290,
      "shares": 2016625947,
      "share_pct": 77.63,
      "source_quality": "official_tdcc_retained_history",
      "market_available_at": "2025-10-23",
      "available_at_policy": "official publication date only; exact time blocked; no prior-week backfill",
      "source_url": "https://www.tdcc.com.tw/portal/zh/smWeb/qryStock",
      "source_hash": "c4a30e9b028da734ddb57229cb48883905f0d8a6da1354267510528938278602",
      "retrieval_time_utc": "2026-07-21T11:10:45+00:00"
    }
  ]
}
