{"code":200,"message":"查詢成功","result":{"marketName":"上市公司","companyId":"3346","tradingUrl":"https://mopsov.twse.com.tw/mops/web/ajax_t211sb05?parameters=cd311393fac67115f8379c750f1259400dc71c55f8e006e5db517b551fd22ffa1ac0acc2404d43cb0735ee58c4dce607ecae32a4d750adfbee83ed57b77e0680","financialUrl":"https://mopsov.twse.com.tw/mops/web/ajax_t211sb01?parameters=cd311393fac67115f8379c750f125940c6aef014273813ea6f45393cd669eea03dbfd310ec954750353eb64544da2970697c3035aecb928c4d5d6cd05f86cceb","data":[["3346","麗清","106/03/10","11:14:37","公告麗清科技股份有限公司受邀參加國票證券主辦2017年投資論壇",{"parameters":{"serialNumber":"2","companyId":"3346","marketKind":"sii","enterDate":"1060310"},"apiName":"t05st01_detail"}],["3346","麗清","106/03/10","11:15:01","公告麗清科技股份有限公司受邀參加富邦證券主辦2017年第一季投資論壇",{"parameters":{"serialNumber":"1","companyId":"3346","marketKind":"sii","enterDate":"1060310"},"apiName":"t05st01_detail"}],["3346","麗清","106/03/16","11:27:23","澄清媒體財訊新聞有關本公司之報導",{"parameters":{"serialNumber":"2","companyId":"3346","marketKind":"sii","enterDate":"1060316"},"apiName":"t05st01_detail"}],["3346","麗清","106/03/24","16:07:43","公告本公司董事會決議通過105年度員工酬勞及董監酬勞分派情形",{"parameters":{"serialNumber":"1","companyId":"3346","marketKind":"sii","enterDate":"1060324"},"apiName":"t05st01_detail"}],["3346","麗清","106/03/24","16:08:18","公告本公司董事會決議召開106年股東常會相關事宜",{"parameters":{"serialNumber":"2","companyId":"3346","marketKind":"sii","enterDate":"1060324"},"apiName":"t05st01_detail"}],["3346","麗清","106/03/24","16:08:35","董事會決議股利分派",{"parameters":{"serialNumber":"3","companyId":"3346","marketKind":"sii","enterDate":"1060324"},"apiName":"t05st01_detail"}],["3346","麗清","106/03/24","16:08:51","公告本公司106年2月自結合併報表部份財務比率",{"parameters":{"serialNumber":"3","companyId":"3346","marketKind":"sii","enterDate":"1060323"},"apiName":"t05st01_detail"}],["3346","麗清","106/03/27","17:20:46","本公司受邀參加臺灣證券交易所舉辦之2017年主題式業績發表會",{"parameters":{"serialNumber":"2","companyId":"3346","marketKind":"sii","enterDate":"1060327"},"apiName":"t05st01_detail"}]],"titles":[{"main":"公司代號","sub":[]},{"main":"公司名稱","sub":[]},{"main":"發言日期","sub":[]},{"main":"發言時間","sub":[]},{"main":"主旨","sub":[]},{"main":"詳細資料","sub":[]}],"companyAbbreviation":"麗清"},"datetime":"115/07/08 17:24:31"}