{
  "family": "tdcc",
  "publication_date": "2026-03-06",
  "ticker": "6669",
  "status": "accepted",
  "filtered_rows": 15,
  "http_status": 200,
  "response_bytes": 76768,
  "source_url": "https://www.tdcc.com.tw/portal/zh/smWeb/qryStock",
  "source_hash": "bca2965a60a01f840802ecc4ba327a88b50afc1769d0a9ef58c7a4ac54950758",
  "retrieval_time_utc": "2026-07-21T11:11:04+00:00",
  "error": "",
  "rows": [
    {
      "publication_date": "2026-03-06",
      "ticker": "6669",
      "market": "TWSE",
      "holding_bucket": "1-999",
      "holder_count": 65724,
      "shares": 3964381,
      "share_pct": 2.13,
      "source_quality": "official_tdcc_retained_history",
      "market_available_at": "2026-03-06",
      "available_at_policy": "official publication date only; exact time blocked; no prior-week backfill",
      "source_url": "https://www.tdcc.com.tw/portal/zh/smWeb/qryStock",
      "source_hash": "bca2965a60a01f840802ecc4ba327a88b50afc1769d0a9ef58c7a4ac54950758",
      "retrieval_time_utc": "2026-07-21T11:11:04+00:00"
    },
    {
      "publication_date": "2026-03-06",
      "ticker": "6669",
      "market": "TWSE",
      "holding_bucket": "1,000-5,000",
      "holder_count": 4571,
      "shares": 7588741,
      "share_pct": 4.08,
      "source_quality": "official_tdcc_retained_history",
      "market_available_at": "2026-03-06",
      "available_at_policy": "official publication date only; exact time blocked; no prior-week backfill",
      "source_url": "https://www.tdcc.com.tw/portal/zh/smWeb/qryStock",
      "source_hash": "bca2965a60a01f840802ecc4ba327a88b50afc1769d0a9ef58c7a4ac54950758",
      "retrieval_time_utc": "2026-07-21T11:11:04+00:00"
    },
    {
      "publication_date": "2026-03-06",
      "ticker": "6669",
      "market": "TWSE",
      "holding_bucket": "5,001-10,000",
      "holder_count": 401,
      "shares": 3020614,
      "share_pct": 1.62,
      "source_quality": "official_tdcc_retained_history",
      "market_available_at": "2026-03-06",
      "available_at_policy": "official publication date only; exact time blocked; no prior-week backfill",
      "source_url": "https://www.tdcc.com.tw/portal/zh/smWeb/qryStock",
      "source_hash": "bca2965a60a01f840802ecc4ba327a88b50afc1769d0a9ef58c7a4ac54950758",
      "retrieval_time_utc": "2026-07-21T11:11:04+00:00"
    },
    {
      "publication_date": "2026-03-06",
      "ticker": "6669",
      "market": "TWSE",
      "holding_bucket": "10,001-15,000",
      "holder_count": 171,
      "shares": 2153344,
      "share_pct": 1.15,
      "source_quality": "official_tdcc_retained_history",
      "market_available_at": "2026-03-06",
      "available_at_policy": "official publication date only; exact time blocked; no prior-week backfill",
      "source_url": "https://www.tdcc.com.tw/portal/zh/smWeb/qryStock",
      "source_hash": "bca2965a60a01f840802ecc4ba327a88b50afc1769d0a9ef58c7a4ac54950758",
      "retrieval_time_utc": "2026-07-21T11:11:04+00:00"
    },
    {
      "publication_date": "2026-03-06",
      "ticker": "6669",
      "market": "TWSE",
      "holding_bucket": "15,001-20,000",
      "holder_count": 125,
      "shares": 2200483,
      "share_pct": 1.18,
      "source_quality": "official_tdcc_retained_history",
      "market_available_at": "2026-03-06",
      "available_at_policy": "official publication date only; exact time blocked; no prior-week backfill",
      "source_url": "https://www.tdcc.com.tw/portal/zh/smWeb/qryStock",
      "source_hash": "bca2965a60a01f840802ecc4ba327a88b50afc1769d0a9ef58c7a4ac54950758",
      "retrieval_time_utc": "2026-07-21T11:11:04+00:00"
    },
    {
      "publication_date": "2026-03-06",
      "ticker": "6669",
      "market": "TWSE",
      "holding_bucket": "20,001-30,000",
      "holder_count": 121,
      "shares": 2993595,
      "share_pct": 1.61,
      "source_quality": "official_tdcc_retained_history",
      "market_available_at": "2026-03-06",
      "available_at_policy": "official publication date only; exact time blocked; no prior-week backfill",
      "source_url": "https://www.tdcc.com.tw/portal/zh/smWeb/qryStock",
      "source_hash": "bca2965a60a01f840802ecc4ba327a88b50afc1769d0a9ef58c7a4ac54950758",
      "retrieval_time_utc": "2026-07-21T11:11:04+00:00"
    },
    {
      "publication_date": "2026-03-06",
      "ticker": "6669",
      "market": "TWSE",
      "holding_bucket": "30,001-40,000",
      "holder_count": 75,
      "shares": 2637806,
      "share_pct": 1.41,
      "source_quality": "official_tdcc_retained_history",
      "market_available_at": "2026-03-06",
      "available_at_policy": "official publication date only; exact time blocked; no prior-week backfill",
      "source_url": "https://www.tdcc.com.tw/portal/zh/smWeb/qryStock",
      "source_hash": "bca2965a60a01f840802ecc4ba327a88b50afc1769d0a9ef58c7a4ac54950758",
      "retrieval_time_utc": "2026-07-21T11:11:04+00:00"
    },
    {
      "publication_date": "2026-03-06",
      "ticker": "6669",
      "market": "TWSE",
      "holding_bucket": "40,001-50,000",
      "holder_count": 54,
      "shares": 2475114,
      "share_pct": 1.33,
      "source_quality": "official_tdcc_retained_history",
      "market_available_at": "2026-03-06",
      "available_at_policy": "official publication date only; exact time blocked; no prior-week backfill",
      "source_url": "https://www.tdcc.com.tw/portal/zh/smWeb/qryStock",
      "source_hash": "bca2965a60a01f840802ecc4ba327a88b50afc1769d0a9ef58c7a4ac54950758",
      "retrieval_time_utc": "2026-07-21T11:11:04+00:00"
    },
    {
      "publication_date": "2026-03-06",
      "ticker": "6669",
      "market": "TWSE",
      "holding_bucket": "50,001-100,000",
      "holder_count": 147,
      "shares": 10616758,
      "share_pct": 5.71,
      "source_quality": "official_tdcc_retained_history",
      "market_available_at": "2026-03-06",
      "available_at_policy": "official publication date only; exact time blocked; no prior-week backfill",
      "source_url": "https://www.tdcc.com.tw/portal/zh/smWeb/qryStock",
      "source_hash": "bca2965a60a01f840802ecc4ba327a88b50afc1769d0a9ef58c7a4ac54950758",
      "retrieval_time_utc": "2026-07-21T11:11:04+00:00"
    },
    {
      "publication_date": "2026-03-06",
      "ticker": "6669",
      "market": "TWSE",
      "holding_bucket": "100,001-200,000",
      "holder_count": 76,
      "shares": 10541618,
      "share_pct": 5.67,
      "source_quality": "official_tdcc_retained_history",
      "market_available_at": "2026-03-06",
      "available_at_policy": "official publication date only; exact time blocked; no prior-week backfill",
      "source_url": "https://www.tdcc.com.tw/portal/zh/smWeb/qryStock",
      "source_hash": "bca2965a60a01f840802ecc4ba327a88b50afc1769d0a9ef58c7a4ac54950758",
      "retrieval_time_utc": "2026-07-21T11:11:04+00:00"
    },
    {
      "publication_date": "2026-03-06",
      "ticker": "6669",
      "market": "TWSE",
      "holding_bucket": "200,001-400,000",
      "holder_count": 59,
      "shares": 16985176,
      "share_pct": 9.13,
      "source_quality": "official_tdcc_retained_history",
      "market_available_at": "2026-03-06",
      "available_at_policy": "official publication date only; exact time blocked; no prior-week backfill",
      "source_url": "https://www.tdcc.com.tw/portal/zh/smWeb/qryStock",
      "source_hash": "bca2965a60a01f840802ecc4ba327a88b50afc1769d0a9ef58c7a4ac54950758",
      "retrieval_time_utc": "2026-07-21T11:11:04+00:00"
    },
    {
      "publication_date": "2026-03-06",
      "ticker": "6669",
      "market": "TWSE",
      "holding_bucket": "400,001-600,000",
      "holder_count": 17,
      "shares": 8299026,
      "share_pct": 4.46,
      "source_quality": "official_tdcc_retained_history",
      "market_available_at": "2026-03-06",
      "available_at_policy": "official publication date only; exact time blocked; no prior-week backfill",
      "source_url": "https://www.tdcc.com.tw/portal/zh/smWeb/qryStock",
      "source_hash": "bca2965a60a01f840802ecc4ba327a88b50afc1769d0a9ef58c7a4ac54950758",
      "retrieval_time_utc": "2026-07-21T11:11:04+00:00"
    },
    {
      "publication_date": "2026-03-06",
      "ticker": "6669",
      "market": "TWSE",
      "holding_bucket": "600,001-800,000",
      "holder_count": 13,
      "shares": 9173089,
      "share_pct": 4.93,
      "source_quality": "official_tdcc_retained_history",
      "market_available_at": "2026-03-06",
      "available_at_policy": "official publication date only; exact time blocked; no prior-week backfill",
      "source_url": "https://www.tdcc.com.tw/portal/zh/smWeb/qryStock",
      "source_hash": "bca2965a60a01f840802ecc4ba327a88b50afc1769d0a9ef58c7a4ac54950758",
      "retrieval_time_utc": "2026-07-21T11:11:04+00:00"
    },
    {
      "publication_date": "2026-03-06",
      "ticker": "6669",
      "market": "TWSE",
      "holding_bucket": "800,001-1,000,000",
      "holder_count": 3,
      "shares": 2641330,
      "share_pct": 1.42,
      "source_quality": "official_tdcc_retained_history",
      "market_available_at": "2026-03-06",
      "available_at_policy": "official publication date only; exact time blocked; no prior-week backfill",
      "source_url": "https://www.tdcc.com.tw/portal/zh/smWeb/qryStock",
      "source_hash": "bca2965a60a01f840802ecc4ba327a88b50afc1769d0a9ef58c7a4ac54950758",
      "retrieval_time_utc": "2026-07-21T11:11:04+00:00"
    },
    {
      "publication_date": "2026-03-06",
      "ticker": "6669",
      "market": "TWSE",
      "holding_bucket": "1,000,001以上",
      "holder_count": 17,
      "shares": 100549716,
      "share_pct": 54.1,
      "source_quality": "official_tdcc_retained_history",
      "market_available_at": "2026-03-06",
      "available_at_policy": "official publication date only; exact time blocked; no prior-week backfill",
      "source_url": "https://www.tdcc.com.tw/portal/zh/smWeb/qryStock",
      "source_hash": "bca2965a60a01f840802ecc4ba327a88b50afc1769d0a9ef58c7a4ac54950758",
      "retrieval_time_utc": "2026-07-21T11:11:04+00:00"
    }
  ]
}
