{
  "family": "tdcc",
  "publication_date": "2026-02-13",
  "ticker": "2454",
  "status": "accepted",
  "filtered_rows": 15,
  "http_status": 200,
  "response_bytes": 76793,
  "source_url": "https://www.tdcc.com.tw/portal/zh/smWeb/qryStock",
  "source_hash": "8d43bdae2f5cffe6e2ece275678bec7592f8b020f29eb877afe8d7e6eea90fa1",
  "retrieval_time_utc": "2026-07-21T11:10:59+00:00",
  "error": "",
  "rows": [
    {
      "publication_date": "2026-02-13",
      "ticker": "2454",
      "market": "TWSE",
      "holding_bucket": "1-999",
      "holder_count": 212185,
      "shares": 21293723,
      "share_pct": 1.32,
      "source_quality": "official_tdcc_retained_history",
      "market_available_at": "2026-02-13",
      "available_at_policy": "official publication date only; exact time blocked; no prior-week backfill",
      "source_url": "https://www.tdcc.com.tw/portal/zh/smWeb/qryStock",
      "source_hash": "8d43bdae2f5cffe6e2ece275678bec7592f8b020f29eb877afe8d7e6eea90fa1",
      "retrieval_time_utc": "2026-07-21T11:10:59+00:00"
    },
    {
      "publication_date": "2026-02-13",
      "ticker": "2454",
      "market": "TWSE",
      "holding_bucket": "1,000-5,000",
      "holder_count": 38778,
      "shares": 64941870,
      "share_pct": 4.04,
      "source_quality": "official_tdcc_retained_history",
      "market_available_at": "2026-02-13",
      "available_at_policy": "official publication date only; exact time blocked; no prior-week backfill",
      "source_url": "https://www.tdcc.com.tw/portal/zh/smWeb/qryStock",
      "source_hash": "8d43bdae2f5cffe6e2ece275678bec7592f8b020f29eb877afe8d7e6eea90fa1",
      "retrieval_time_utc": "2026-07-21T11:10:59+00:00"
    },
    {
      "publication_date": "2026-02-13",
      "ticker": "2454",
      "market": "TWSE",
      "holding_bucket": "5,001-10,000",
      "holder_count": 2757,
      "shares": 20288556,
      "share_pct": 1.26,
      "source_quality": "official_tdcc_retained_history",
      "market_available_at": "2026-02-13",
      "available_at_policy": "official publication date only; exact time blocked; no prior-week backfill",
      "source_url": "https://www.tdcc.com.tw/portal/zh/smWeb/qryStock",
      "source_hash": "8d43bdae2f5cffe6e2ece275678bec7592f8b020f29eb877afe8d7e6eea90fa1",
      "retrieval_time_utc": "2026-07-21T11:10:59+00:00"
    },
    {
      "publication_date": "2026-02-13",
      "ticker": "2454",
      "market": "TWSE",
      "holding_bucket": "10,001-15,000",
      "holder_count": 954,
      "shares": 11956872,
      "share_pct": 0.74,
      "source_quality": "official_tdcc_retained_history",
      "market_available_at": "2026-02-13",
      "available_at_policy": "official publication date only; exact time blocked; no prior-week backfill",
      "source_url": "https://www.tdcc.com.tw/portal/zh/smWeb/qryStock",
      "source_hash": "8d43bdae2f5cffe6e2ece275678bec7592f8b020f29eb877afe8d7e6eea90fa1",
      "retrieval_time_utc": "2026-07-21T11:10:59+00:00"
    },
    {
      "publication_date": "2026-02-13",
      "ticker": "2454",
      "market": "TWSE",
      "holding_bucket": "15,001-20,000",
      "holder_count": 516,
      "shares": 9137156,
      "share_pct": 0.56,
      "source_quality": "official_tdcc_retained_history",
      "market_available_at": "2026-02-13",
      "available_at_policy": "official publication date only; exact time blocked; no prior-week backfill",
      "source_url": "https://www.tdcc.com.tw/portal/zh/smWeb/qryStock",
      "source_hash": "8d43bdae2f5cffe6e2ece275678bec7592f8b020f29eb877afe8d7e6eea90fa1",
      "retrieval_time_utc": "2026-07-21T11:10:59+00:00"
    },
    {
      "publication_date": "2026-02-13",
      "ticker": "2454",
      "market": "TWSE",
      "holding_bucket": "20,001-30,000",
      "holder_count": 540,
      "shares": 13335431,
      "share_pct": 0.83,
      "source_quality": "official_tdcc_retained_history",
      "market_available_at": "2026-02-13",
      "available_at_policy": "official publication date only; exact time blocked; no prior-week backfill",
      "source_url": "https://www.tdcc.com.tw/portal/zh/smWeb/qryStock",
      "source_hash": "8d43bdae2f5cffe6e2ece275678bec7592f8b020f29eb877afe8d7e6eea90fa1",
      "retrieval_time_utc": "2026-07-21T11:10:59+00:00"
    },
    {
      "publication_date": "2026-02-13",
      "ticker": "2454",
      "market": "TWSE",
      "holding_bucket": "30,001-40,000",
      "holder_count": 292,
      "shares": 10319980,
      "share_pct": 0.64,
      "source_quality": "official_tdcc_retained_history",
      "market_available_at": "2026-02-13",
      "available_at_policy": "official publication date only; exact time blocked; no prior-week backfill",
      "source_url": "https://www.tdcc.com.tw/portal/zh/smWeb/qryStock",
      "source_hash": "8d43bdae2f5cffe6e2ece275678bec7592f8b020f29eb877afe8d7e6eea90fa1",
      "retrieval_time_utc": "2026-07-21T11:10:59+00:00"
    },
    {
      "publication_date": "2026-02-13",
      "ticker": "2454",
      "market": "TWSE",
      "holding_bucket": "40,001-50,000",
      "holder_count": 228,
      "shares": 10388371,
      "share_pct": 0.64,
      "source_quality": "official_tdcc_retained_history",
      "market_available_at": "2026-02-13",
      "available_at_policy": "official publication date only; exact time blocked; no prior-week backfill",
      "source_url": "https://www.tdcc.com.tw/portal/zh/smWeb/qryStock",
      "source_hash": "8d43bdae2f5cffe6e2ece275678bec7592f8b020f29eb877afe8d7e6eea90fa1",
      "retrieval_time_utc": "2026-07-21T11:10:59+00:00"
    },
    {
      "publication_date": "2026-02-13",
      "ticker": "2454",
      "market": "TWSE",
      "holding_bucket": "50,001-100,000",
      "holder_count": 580,
      "shares": 41652880,
      "share_pct": 2.59,
      "source_quality": "official_tdcc_retained_history",
      "market_available_at": "2026-02-13",
      "available_at_policy": "official publication date only; exact time blocked; no prior-week backfill",
      "source_url": "https://www.tdcc.com.tw/portal/zh/smWeb/qryStock",
      "source_hash": "8d43bdae2f5cffe6e2ece275678bec7592f8b020f29eb877afe8d7e6eea90fa1",
      "retrieval_time_utc": "2026-07-21T11:10:59+00:00"
    },
    {
      "publication_date": "2026-02-13",
      "ticker": "2454",
      "market": "TWSE",
      "holding_bucket": "100,001-200,000",
      "holder_count": 489,
      "shares": 69969168,
      "share_pct": 4.36,
      "source_quality": "official_tdcc_retained_history",
      "market_available_at": "2026-02-13",
      "available_at_policy": "official publication date only; exact time blocked; no prior-week backfill",
      "source_url": "https://www.tdcc.com.tw/portal/zh/smWeb/qryStock",
      "source_hash": "8d43bdae2f5cffe6e2ece275678bec7592f8b020f29eb877afe8d7e6eea90fa1",
      "retrieval_time_utc": "2026-07-21T11:10:59+00:00"
    },
    {
      "publication_date": "2026-02-13",
      "ticker": "2454",
      "market": "TWSE",
      "holding_bucket": "200,001-400,000",
      "holder_count": 346,
      "shares": 97824399,
      "share_pct": 6.09,
      "source_quality": "official_tdcc_retained_history",
      "market_available_at": "2026-02-13",
      "available_at_policy": "official publication date only; exact time blocked; no prior-week backfill",
      "source_url": "https://www.tdcc.com.tw/portal/zh/smWeb/qryStock",
      "source_hash": "8d43bdae2f5cffe6e2ece275678bec7592f8b020f29eb877afe8d7e6eea90fa1",
      "retrieval_time_utc": "2026-07-21T11:10:59+00:00"
    },
    {
      "publication_date": "2026-02-13",
      "ticker": "2454",
      "market": "TWSE",
      "holding_bucket": "400,001-600,000",
      "holder_count": 124,
      "shares": 60973874,
      "share_pct": 3.8,
      "source_quality": "official_tdcc_retained_history",
      "market_available_at": "2026-02-13",
      "available_at_policy": "official publication date only; exact time blocked; no prior-week backfill",
      "source_url": "https://www.tdcc.com.tw/portal/zh/smWeb/qryStock",
      "source_hash": "8d43bdae2f5cffe6e2ece275678bec7592f8b020f29eb877afe8d7e6eea90fa1",
      "retrieval_time_utc": "2026-07-21T11:10:59+00:00"
    },
    {
      "publication_date": "2026-02-13",
      "ticker": "2454",
      "market": "TWSE",
      "holding_bucket": "600,001-800,000",
      "holder_count": 79,
      "shares": 55026965,
      "share_pct": 3.43,
      "source_quality": "official_tdcc_retained_history",
      "market_available_at": "2026-02-13",
      "available_at_policy": "official publication date only; exact time blocked; no prior-week backfill",
      "source_url": "https://www.tdcc.com.tw/portal/zh/smWeb/qryStock",
      "source_hash": "8d43bdae2f5cffe6e2ece275678bec7592f8b020f29eb877afe8d7e6eea90fa1",
      "retrieval_time_utc": "2026-07-21T11:10:59+00:00"
    },
    {
      "publication_date": "2026-02-13",
      "ticker": "2454",
      "market": "TWSE",
      "holding_bucket": "800,001-1,000,000",
      "holder_count": 44,
      "shares": 39712769,
      "share_pct": 2.47,
      "source_quality": "official_tdcc_retained_history",
      "market_available_at": "2026-02-13",
      "available_at_policy": "official publication date only; exact time blocked; no prior-week backfill",
      "source_url": "https://www.tdcc.com.tw/portal/zh/smWeb/qryStock",
      "source_hash": "8d43bdae2f5cffe6e2ece275678bec7592f8b020f29eb877afe8d7e6eea90fa1",
      "retrieval_time_utc": "2026-07-21T11:10:59+00:00"
    },
    {
      "publication_date": "2026-02-13",
      "ticker": "2454",
      "market": "TWSE",
      "holding_bucket": "1,000,001以上",
      "holder_count": 242,
      "shares": 1077090168,
      "share_pct": 67.15,
      "source_quality": "official_tdcc_retained_history",
      "market_available_at": "2026-02-13",
      "available_at_policy": "official publication date only; exact time blocked; no prior-week backfill",
      "source_url": "https://www.tdcc.com.tw/portal/zh/smWeb/qryStock",
      "source_hash": "8d43bdae2f5cffe6e2ece275678bec7592f8b020f29eb877afe8d7e6eea90fa1",
      "retrieval_time_utc": "2026-07-21T11:10:59+00:00"
    }
  ]
}
