{"stat":"OK","date":"20230331","title":"112年03月31日 變更交易","fields":["證券代號","證券名稱","分盤集合競價(以**表示)"],"data":[["1213","大飲","  "],["1472","三洋實業","  "],["1512","瑞利","**"],["1538","正峰","**"],["2025","千興","  "],["2321","東訊","**"],["2443","昶虹","**"],["3043","科風","**"],["3321","同泰","  "],["3536","誠創","**"],["4943","康控-KY","**"],["6225","天瀚","  "],["6541","泰福-KY","  "],["8101","華冠","  "],["9110","越南控-DR","  "]],"notes":["**代表上市證券除應預先收足款券外，其交易採分盤集合競價方式，該方式係採每30分鐘以人工管制之撮合終端機執行撮合作業一次為原則，並得視交易情形因應公告調整撮合時間。","當日如有臨時新增之變更交易有價證券標的，網頁右上角會呈現點選框，屆時請點選明細查詢，另外，歷史資料也可點選此 <a href='/zh/trading/bfihbu.html' target='_blank'>連結<\u002fa> 查詢。"],"total":15}