{"code":200,"message":"查詢成功","result":{"marketName":"上市公司","companyId":"2454","tradingUrl":"https://mopsov.twse.com.tw/mops/web/ajax_t211sb05?parameters=d4b8b41be525ddda85695f83e143c1aeaf4b09986042af255dd32918ada39d821ac0acc2404d43cb0735ee58c4dce607ecae32a4d750adfbee83ed57b77e0680","financialUrl":"https://mopsov.twse.com.tw/mops/web/ajax_t211sb01?parameters=d4b8b41be525ddda85695f83e143c1ae573d6d6ec14b88c2e6e3466804c5469eec536dfd5187971b86bc38d2b44d463e697c3035aecb928c4d5d6cd05f86cceb","data":[["2454","聯發科","114/03/10","16:55:52","聯發科技114年2月份自結合併營收淨額公告",{"parameters":{"enterDate":"1140310","serialNumber":"1","companyId":"2454","marketKind":"sii"},"apiName":"t05st01_detail"}],["2454","聯發科","114/03/13","17:16:44","代重要子公司Gaintech Co. Limited公告董事會決議發放股利",{"parameters":{"enterDate":"1140307","serialNumber":"1","companyId":"2454","marketKind":"sii"},"apiName":"t05st01_detail"}],["2454","聯發科","114/03/13","17:17:16","代重要子公司MediaTek Investment Singapore Pte. Ltd.\r\n公告董事會決議發放股利",{"parameters":{"enterDate":"1140307","serialNumber":"2","companyId":"2454","marketKind":"sii"},"apiName":"t05st01_detail"}],["2454","聯發科","114/03/13","17:17:44","代重要子公司MediaTek Investment Singapore Pte. Ltd.\r\n公告董事會決議通過辦理現金減資案",{"parameters":{"enterDate":"1140307","serialNumber":"3","companyId":"2454","marketKind":"sii"},"apiName":"t05st01_detail"}],["2454","聯發科","114/03/17","17:08:04","公告本公司參與機構投資人說明會",{"parameters":{"enterDate":"1140317","serialNumber":"2","companyId":"2454","marketKind":"sii"},"apiName":"t05st01_detail"}],["2454","聯發科","114/03/18","17:38:58","代子公司Gaintech Co. Limited（下稱「Gaintech」）\r\n公告處分有價證券",{"parameters":{"enterDate":"1140318","serialNumber":"1","companyId":"2454","marketKind":"sii"},"apiName":"t05st01_detail"}],["2454","聯發科","114/03/20","17:16:31","代重要子公司MEDIATEK SINGAPORE PTE. LTD.\r\n公告董事會決議發放股利",{"parameters":{"enterDate":"1140317","serialNumber":"1","companyId":"2454","marketKind":"sii"},"apiName":"t05st01_detail"}],["2454","聯發科","114/03/21","17:14:27","(補充114/03/18公告) 代子公司Gaintech Co. Limited\r\n（下稱「Gaintech」）公告處分有價證券",{"parameters":{"enterDate":"1140321","serialNumber":"1","companyId":"2454","marketKind":"sii"},"apiName":"t05st01_detail"}]],"titles":[{"main":"公司代號","sub":[]},{"main":"公司名稱","sub":[]},{"main":"發言日期","sub":[]},{"main":"發言時間","sub":[]},{"main":"主旨","sub":[]},{"main":"詳細資料","sub":[]}],"companyAbbreviation":"聯發科"},"datetime":"115/07/07 15:15:29"}