{"code":200,"message":"查詢成功","result":{"marketName":"上市公司","companyId":"2882","tradingUrl":"https://mopsov.twse.com.tw/mops/web/ajax_t211sb05?parameters=f62d62a3ece973a35212673eda896854af4b09986042af255dd32918ada39d821ac0acc2404d43cb0735ee58c4dce607ecae32a4d750adfbee83ed57b77e0680","financialUrl":"https://mopsov.twse.com.tw/mops/web/ajax_t211sb01?parameters=f62d62a3ece973a35212673eda896854573d6d6ec14b88c2e6e3466804c5469eec536dfd5187971b86bc38d2b44d463e697c3035aecb928c4d5d6cd05f86cceb","data":[["2882","國泰金","115/04/09","17:17:57","代子公司國泰綜合證券公告向國泰世華商業銀行(股)公司取得使用權資產",{"parameters":{"enterDate":"1150409","serialNumber":"1","companyId":"2882","marketKind":"sii"},"apiName":"t05st01_detail"}],["2882","國泰金","115/04/13","17:10:36","公告本公司受邀參加HSBC舉辦之投資人會議",{"parameters":{"enterDate":"1150413","serialNumber":"1","companyId":"2882","marketKind":"sii"},"apiName":"t05st01_detail"}],["2882","國泰金","115/04/13","17:47:28","代子公司國泰世華商業銀行公告授信資產之轉讓",{"parameters":{"enterDate":"1150413","serialNumber":"2","companyId":"2882","marketKind":"sii"},"apiName":"t05st01_detail"}],["2882","國泰金","115/04/14","17:02:14","代國泰風能控股公告董事會通過114年度虧損撥補案",{"parameters":{"enterDate":"1150410","serialNumber":"1","companyId":"2882","marketKind":"sii"},"apiName":"t05st01_detail"}],["2882","國泰金","115/04/15","16:59:53","公告本公司暨主要子公司115年03月自結合併稅後損益",{"parameters":{"enterDate":"1150415","serialNumber":"1","companyId":"2882","marketKind":"sii"},"apiName":"t05st01_detail"}],["2882","國泰金","115/04/15","17:33:58","代世越銀行補充公告盈餘轉增資",{"parameters":{"enterDate":"1150415","serialNumber":"3","companyId":"2882","marketKind":"sii"},"apiName":"t05st01_detail"}],["2882","國泰金","115/04/23","22:40:11","代CATHAYLIFE SINGAPORE PTE. LTD.公告完成美元5億元\r\n十五年期無擔保累積次順位普通公司債定價",{"parameters":{"enterDate":"1150423","serialNumber":"1","companyId":"2882","marketKind":"sii"},"apiName":"t05st01_detail"}],["2882","國泰金","115/04/27","17:00:54","代子公司國泰投信公告董事會(代行使股東會職權)重要決議事項",{"parameters":{"enterDate":"1150422","serialNumber":"2","companyId":"2882","marketKind":"sii"},"apiName":"t05st01_detail"}],["2882","國泰金","115/04/27","17:01:39","代國泰投顧公告董事會(代行股東會職權)重要決議事項",{"parameters":{"enterDate":"1150424","serialNumber":"1","companyId":"2882","marketKind":"sii"},"apiName":"t05st01_detail"}],["2882","國泰金","115/04/28","16:05:05","本公司代子公司國泰人壽公告擬依持股比例參與陸家嘴國泰人壽現金增資人民幣10億元",{"parameters":{"enterDate":"1150428","serialNumber":"2","companyId":"2882","marketKind":"sii"},"apiName":"t05st01_detail"}],["2882","國泰金","115/04/28","16:30:13","董事會決議分派普通股股利每股3.5元",{"parameters":{"enterDate":"1150428","serialNumber":"3","companyId":"2882","marketKind":"sii"},"apiName":"t05st01_detail"}],["2882","國泰金","115/04/28","16:30:46","分派甲種特別股股利",{"parameters":{"enterDate":"1150428","serialNumber":"4","companyId":"2882","marketKind":"sii"},"apiName":"t05st01_detail"}],["2882","國泰金","115/04/28","16:31:21","分派乙種特別股股利",{"parameters":{"enterDate":"1150428","serialNumber":"5","companyId":"2882","marketKind":"sii"},"apiName":"t05st01_detail"}],["2882","國泰金","115/04/28","16:32:32","代子公司國泰綜合證券公告董事會(代行股東會職權)\r\n重要決議事項",{"parameters":{"enterDate":"1150422","serialNumber":"1","companyId":"2882","marketKind":"sii"},"apiName":"t05st01_detail"}],["2882","國泰金","115/04/28","16:32:55","代子公司國泰人壽公告董事會（代行股東會職權）重要\r\n決議事項",{"parameters":{"enterDate":"1150424","serialNumber":"2","companyId":"2882","marketKind":"sii"},"apiName":"t05st01_detail"}],["2882","國泰金","115/04/28","16:33:22","代子公司國泰產險公告董事會(代行使股東會職權)重要決議\r\n事項",{"parameters":{"enterDate":"1150427","serialNumber":"2","companyId":"2882","marketKind":"sii"},"apiName":"t05st01_detail"}],["2882","國泰金","115/04/28","16:33:38","代國泰期貨股份有限公司公告內部稽核主管異動事宜",{"parameters":{"enterDate":"1150428","serialNumber":"1","companyId":"2882","marketKind":"sii"},"apiName":"t05st01_detail"}],["2882","國泰金","115/04/28","16:34:01","代子公司國泰世華銀行公告董事會(代行股東會職權)\r\n重要決議事項",{"parameters":{"enterDate":"1150427","serialNumber":"1","companyId":"2882","marketKind":"sii"},"apiName":"t05st01_detail"}],["2882","國泰金","115/04/28","16:36:35","代子公司國泰世華商業銀行公告授信資產之轉讓",{"parameters":{"enterDate":"1150428","serialNumber":"6","companyId":"2882","marketKind":"sii"},"apiName":"t05st01_detail"}],["2882","國泰金","115/04/29","17:04:16","代子公司國泰綜合證券公告會計主管辭任事宜",{"parameters":{"enterDate":"1150429","serialNumber":"1","companyId":"2882","marketKind":"sii"},"apiName":"t05st01_detail"}],["2882","國泰金","115/04/29","17:06:12","公告本公司115年第一季法人說明會日期",{"parameters":{"enterDate":"1150429","serialNumber":"2","companyId":"2882","marketKind":"sii"},"apiName":"t05st01_detail"}]],"titles":[{"main":"公司代號","sub":[]},{"main":"公司名稱","sub":[]},{"main":"發言日期","sub":[]},{"main":"發言時間","sub":[]},{"main":"主旨","sub":[]},{"main":"詳細資料","sub":[]}],"companyAbbreviation":"國泰金"},"datetime":"115/07/07 15:16:55"}