{"code":200,"message":"查詢成功","result":{"marketName":"上櫃公司","companyId":"6187","data":[["5","115/06/26","17:02:38","盧慧萱                                                                                                                                                                                                  ","董事長特助          ","(07)607-1828        ","公告本公司115年度股東常會通過解除新任董事及其代表人\r\n有關公司法第209條競業禁止之限制                                                                                                ","第21款","115/06/26","1.股東會決議日:115/06/26\n2.許可從事競業行為之董事姓名及職稱:\n (1)董事：盧鏡來\n (2)董事：歐承恩\n (3)董事：陳健章\n (4)董事：邱黃敬瀚\n (8)董事：豊喬投資(股)公司代表人：鍾雨茹\n (6)董事：進誠投資有限公司代表人：蔡進樹\n (7)獨立董事：光灼華\n (8)獨立董事：周煥銘\n (9)獨立董事：李明憲\n3.許可從事競業行為之項目:以無損於本公司之利益為限\n董事:盧鏡來\n     聯潤科技股份有限公司董事長\n     三雄精密工業股份有限公司董事長\n     萬潤科技日本株式會社代表取締役\n     All Ring Tech Malaysia SDN. BHD.董事\n     All Ring Tech USA LLC.董事\n     鉑潤投資股份有限公司董事長\n     萬潤科技精機(昆山)董事長\n     昆山萬潤電子董事長\n     豊喬投資股份有限公司董事\n     長廣精機股份有限公司董事\n     鳳凰創新創業投資股份有限公司董事\n     鳳凰肆創新創業投資股份有限公司董事\n     鳳凰陸創新創業投資股份有限公司董事\n     鳳凰柒創新創業投資股份有限公司董事\n     鳳凰捌創新創業投資股份有限公司董事\n     鳳凰十創新創業投資股份有限公司董事\n     北科之星貳創業投資股份有限公司董事\n董事:歐承恩\n     聯潤科技股份有限公司董事\n     三雄精密工業股份有限公司董事\n     鉑睿股份有限公司董事長\n     光陽光電股份有限公司董事\n董事:陳健章\n     府都建設股份有限公司董事\n     普田營造工程股份有限公司董事長\n董事:邱黃敬瀚\n     瀚霖建設(股)公司董事長\n董事:豊喬投資(股)公司代表人：鍾雨茹\n     豊喬投資股份有限公司董事長\n     昇冠投資股份有限公司監察人\n董事:進誠投資有限公司代表人：蔡進樹\n     進誠投資有限公司董事長\n     鼎笈機電工程有限公司董事長\n     進豐興交通有限公司董事長\n     楠峰機電有限公司董事長\n     晉成科技股份有限公司監察人\n獨立董事:光灼華\n         國立中山大學機械工程學系榮譽退休教授\n獨立董事:周煥銘\n         崑山科技大學智慧機器人工程系講座教授\n獨立董事:李明憲\n         志成合署會計師事務所副所長\n         國立成功大學兼任副教授\n         台灣神隆股份有限公司獨立董事\n         智崴資訊科技股份有限公司獨立董事\n         寶雅國際股份有限公司獨立董事\n4.許可從事競業行為之期間:任職董事職務期間\n5.決議情形（請依公司法第209條說明表決結果）:經115年6月26日\n股東常會表決通過，同意解除上述董事之競業禁止。\n6.所許可之競業行為如屬大陸地區事業之營業者，董事姓名及職稱\n（非屬大陸地區事業之營業者，以下請輸〝不適用〞）:\n董事：盧鏡來\n7.所擔任該大陸地區事業之公司名稱及職務:\n盧鏡來 昆山萬潤電子科技有限公司董事長；萬潤科技精機(昆山)有限公司董事長\n8.所擔任該大陸地區事業地址:\n昆山萬潤電子科技有限公司:江蘇省昆山市玉山鎮山淞路299號\n萬潤科技精機(昆山)有限公司:江蘇省昆山市玉山鎮山淞路299號\n9.所擔任該大陸地區事業營業項目:研發、設計及生產電子專用設備、測試儀器\n及其配件；銷售自產產品並提供相應的技術與檢測服務\n10.對本公司財務業務之影響程度:無。\n11.董事如有對該大陸地區事業從事投資者，其投資金額及持股比例:無。\n12.其他應敘明事項:無。\n"]],"footer":["以上資料均由各公司依發言當時所屬市場別之規定申報後，由本系統對外公佈，資料如有虛偽不實，均由該公司負責。"],"header":{"note":[],"subTitle":[],"mainTitle":[]},"titles":[{"main":"序號","sub":[]},{"main":"發言日期","sub":[]},{"main":"發言時間","sub":[]},{"main":"發言人","sub":[]},{"main":"發言人職稱","sub":[]},{"main":"發言人電話","sub":[]},{"main":"主旨","sub":[]},{"main":"符合條款","sub":[]},{"main":"事實發生日","sub":[]},{"main":"說明","sub":[]}],"companyAbbreviation":"萬潤"},"datetime":"115/07/07 15:20:58"}