{"code":200,"message":"查詢成功","result":{"reportType":"合併","year":"115","reportList":[["營業活動之現金流量－間接法","",""],["　繼續營業單位稅前淨利（淨損）","2,346,731","2,133,405"],["　本期稅前淨利（淨損）","2,346,731","2,133,405"],["　　　折舊費用","2,199,157","2,249,944"],["　　　攤銷費用","5,719","5,357"],["　　　預期信用減損損失（利益）數／呆帳費用提列（轉列收入）數","101","7,604"],["　　　透過損益按公允價值衡量金融資產及負債之淨損失（利益）","-457,198","863,858"],["　　　利息費用","424,336","220,226"],["　　　利息收入","-915,644","-576,003"],["　　　股利收入","-14,657","-8,253"],["　　　採用權益法認列之關聯企業及合資損失（利益）之份額","-7,162","-22,681"],["　　　處分及報廢不動產、廠房及設備損失（利益）","-22,370","-4,106"],["　　　其他項目","-91,872","77,178"],["　　　收益費損項目合計","1,120,410","2,813,124"],["　　　　應收帳款（增加）減少","-24,624","-528,374"],["　　　　存貨（增加）減少","-501,157","-831,775"],["　　　　預付款項（增加）減少","-53,191","65,838"],["　　　　其他金融資產（增加）減少","-347,018","21,224"],["　　　　其他營業資產（增加）減少","-107,840","-109,961"],["　　　　與營業活動相關之資產之淨變動合計","-1,033,830","-1,383,048"],["　　　　合約負債增加（減少）","-1,648,471","-1,465,527"],["　　　　應付帳款增加（減少）","-257,355","-594,533"],["　　　　淨確定福利負債增加（減少）","21,070","92,988"],["　　　　其他營業負債增加（減少）","114,756","196,900"],["　　　　與營業活動相關之負債之淨變動合計","-1,770,000","-1,770,172"],["　　　與營業活動相關之資產及負債之淨變動合計","-2,803,830","-3,153,220"],["　　調整項目合計","-1,683,420","-340,096"],["　營運產生之現金流入（流出）","663,311","1,793,309"],["　收取之利息","841,193","405,183"],["　收取之股利","14,657","8,253"],["　支付之利息","-820,770","-797,879"],["　退還（支付）之所得稅","-25,089","-383,109"],["營業活動之淨現金流入（流出）","673,302","1,025,757"],["投資活動之現金流量","",""],["　取得透過其他綜合損益按公允價值衡量之金融資產","-7,993","-33,385"],["　透過其他綜合損益按公允價值衡量之金融資產減資退回股款","21,335","4,647"],["　取得不動產、廠房及設備","-3,460,304","-11,557,104"],["　處分不動產、廠房及設備","34,657","376"],["　取得無形資產","-85","-4,890"],["　其他金融資產增加","0","-2,753,182"],["　其他金融資產減少","14,507,282","0"],["　其他投資活動","1,102,572","132,628"],["　投資活動之淨現金流入（流出）","12,197,464","-14,210,910"],["籌資活動之現金流量","",""],["　短期借款增加","0","4,745,983"],["　短期借款減少","-7,877,318","0"],["　應付短期票券增加","3,557,883","0"],["　應付短期票券減少","0","-699,962"],["　償還公司債","-110,731","0"],["　舉借長期借款","3,173,541","1,739,701"],["　償還長期借款","-6,555,525","-562,032"],["　存入保證金增加","42,350","30,250"],["　其他應付款－關係人減少","0","-340,000"],["　租賃本金償還","-44,216","-47,636"],["　發放現金股利","-956,227","-2,390,569"],["　籌資活動之淨現金流入（流出）","-8,770,243","2,475,735"],["匯率變動對現金及約當現金之影響","542,889","625,648"],["本期現金及約當現金增加（減少）數","4,643,412","-10,083,770"],["期初現金及約當現金餘額","19,484,156","38,929,337"],["期末現金及約當現金餘額","24,127,568","28,845,567"],["　資產負債表帳列之現金及約當現金","24,127,568","28,845,567"]],"season":"1","urlList":[{"url":"https://mopsov.twse.com.tw/server-java/t164sb01?step=1&CO_ID=6488&SYEAR=2026&SSEASON=1&REPORT_ID=C","name":"XBRL資訊平台"},{"url":"http://doc.twse.com.tw/server-java/t57sb01?step=1&colorchg=1&co_id=6488&year=115&mtype=A","name":"電子書查詢"}],"titles":[{"main":"會計項目","sub":[]},{"main":"115年01月01日至115年03月31日","sub":[{"main":"金額","sub":[]}]},{"main":"114年01月01日至114年03月31日","sub":[{"main":"金額","sub":[]}]}],"fiscalYear":" ","subsidiary":[],"companyAbbreviation":"環球晶"},"datetime":"115/07/07 15:34:38"}